<?xml version="1.0" ?>
<TS_PROFILE>
	<TS_NAME>ITS3WN01-HK</TS_NAME>
	<STRESS_TEST>
		<ENABLED>NO</ENABLED>
		<NUM_EXECUTION> 20 </NUM_EXECUTION>
	</STRESS_TEST>
	<PROD_GRP>
		<PROD>
			<NAME> RBR20v1 </NAME>
			<SUB_DIR> RBR20v1 </SUB_DIR>
			<DUT_POWER_TYPE>12VDC</DUT_POWER_TYPE>
			<RGM_TEST_SUITE> suite.xml </RGM_TEST_SUITE>
			<NUMBER_TESTBEDS>10</NUMBER_TESTBEDS>
			<MAC_ENTRY>ENABLED</MAC_ENTRY>
			<FW_ENTRY>ENABLED</FW_ENTRY>
			<SKU_SN_PREFIX/>
			<QR_CODE>
				<SEPARATOR_LIST>
					<SEPARATOR>,</SEPARATOR>
					<SEPARATOR>;</SEPARATOR>
				</SEPARATOR_LIST>
				<QR_CODE_ITEMS>
					<QR_CODE_ITEM name="SN" validation="SerialNumService"  full_string_pattern="True"/>
					<QR_CODE_ITEM name="MAC" validation="MACAddressService"  full_string_pattern="True"/>
					<QR_CODE_ITEM name="SSID" validation="(ORBI[0-9]+)" full_string_pattern="True" />
					<QR_CODE_ITEM name="PWD" validation="([a-z]{5,}[0-9]{3})" full_string_pattern="True" />
				</QR_CODE_ITEMS>
			</QR_CODE>
		</PROD>
	</PROD_GRP>
	<CONFIG_DIR>/opt/its3/TSLIB/config/TB</CONFIG_DIR>
	<RESULT_DIR>/tmp/its3/test_results</RESULT_DIR>
	<ATTENUATOR_VALUE>-10</ATTENUATOR_VALUE>
	<FIXTURE_USAGE>
		<SHOW_USAGE_COUNT>YES</SHOW_USAGE_COUNT>
		<FIXTURE_COUNTER_DIR>/tmp/its3/cable_counter</FIXTURE_COUNTER_DIR>
		<MAX_LIMIT>500</MAX_LIMIT>
	</FIXTURE_USAGE>
	<CALIBRATION>
		<ENABLED>YES</ENABLED>
		<CALIBRATION_DIR>/tmp/its3/cal_data</CALIBRATION_DIR>
		<MAX_LIMIT>100</MAX_LIMIT>
	</CALIBRATION>
	<GOLDEN_SAMPLE_DATA>
		<GOLDEN_SAMPLE_DIR> /tmp/its3/golden_sample_data </GOLDEN_SAMPLE_DIR>
	</GOLDEN_SAMPLE_DATA>
	<CORP_NETWORK>www.netgear.com</CORP_NETWORK>
	<DUT_TEST_DATA>
		<DUT_DIR>/tmp/its3/dut_test_data</DUT_DIR>
	</DUT_TEST_DATA>
	<DB_SERVER>
		<IP_ADDR> 192.168.5.201 </IP_ADDR>
		<USER> pte </USER>
		<PASSWD> pte </PASSWD>
		<DATABASE> its_db </DATABASE>
		<ONLINE>YES</ONLINE>
		<NUM_TRIES>3</NUM_TRIES>
		<MONITORING_INTERVAL>30</MONITORING_INTERVAL>
	</DB_SERVER>
	<SHOP_FLOOR>
		<IP_ADDR> 192.168.5.201 </IP_ADDR>
		<USER> pte </USER>
		<PASSWD> pte </PASSWD>
		<DATABASE> its_db </DATABASE>
		<STATION_TYPE>ITS3_WN</STATION_TYPE>
		<ONLINE>NO</ONLINE>
		<NUM_TRIES>3</NUM_TRIES>
		<MONITORING_INTERVAL>30</MONITORING_INTERVAL>
	</SHOP_FLOOR>
</TS_PROFILE>
